sigma/backends/qradar/__init__.py
sigma/backends/qradar/qradar.py
sigma/pipelines/qradar/__init__.py
sigma/pipelines/qradar/qradar.py
pysigma_backend_qradar-0.3.3.dist-info/LICENSE
pysigma_backend_qradar-0.3.3.dist-info/WHEEL
pysigma_backend_qradar-0.3.3.dist-info/METADATA
pysigma_backend_qradar-0.3.3.dist-info/RECORD
