Metadata-Version: 2.1
Name: pysigma-backend-qradar
Version: 0.3.3
Summary: pySigma Qradar backend
License: LGPL-2.1-only
Author: nNipsx-Sec
Author-email: nnipsxz@gmail.com
Requires-Python: >=3.8,<4.0
Classifier: License :: OSI Approved
Classifier: Programming Language :: Python :: 3
Classifier: Programming Language :: Python :: 3.8
Classifier: Programming Language :: Python :: 3.9
Classifier: Programming Language :: Python :: 3.10
Requires-Dist: pysigma (>=0.9.4,<0.10.0)
